LICENSE
README.md
setup.py
pystochastica/__init__.py
pystochastica.egg-info/PKG-INFO
pystochastica.egg-info/SOURCES.txt
pystochastica.egg-info/dependency_links.txt
pystochastica.egg-info/top_level.txt
pystochastica/discrete/core/__init__.py
pystochastica/discrete/core/_jointdist.py
pystochastica/discrete/core/_randvar_base.py
pystochastica/discrete/core/_sample_base.py
pystochastica/discrete/dsp/__init__.py
pystochastica/discrete/dsp/_dsp.py
pystochastica/discrete/dsp/_randwalk.py
pystochastica/discrete/optimisers/__init__.py
pystochastica/discrete/optimisers/_meanvar.py
pystochastica/discrete/samples/__init__.py
pystochastica/discrete/samples/_samples.py
pystochastica/discrete/simulations/__init__.py
pystochastica/discrete/simulations/_simulation.py
pystochastica/discrete/utils/__init__.py
pystochastica/discrete/utils/dict_conversions.py
pystochastica/discrete/utils/dict_convolution.py
pystochastica/discrete/utils/dict_multiply.py
pystochastica/discrete/utils/jointdist_generators.py
pystochastica/discrete/variables/__init__.py
pystochastica/discrete/variables/_randvar.py
pystochastica/discrete/vectors/__init__.py
pystochastica/discrete/vectors/_randvec.py